{"documentCount":4,"nextId":4,"documentIds":{"0":1091,"1":1095,"2":1099,"3":1103},"fieldIds":{"title_en":0,"title_th":1,"description_en":2,"description_th":3},"fieldLength":{"0":[4,3,6,1],"1":[4,3,6,1],"2":[4,3,6,1],"3":[4,3,6,1]},"averageFieldLength":[4,3,6,1],"storedFields":{"0":{"id":1091,"title_en":"land in Chumphon #3","title_th":"ที่ดิน ในชุมพร #3","province":"Chumphon","province_th":"ชุมพร","type":"land","price":11714354,"priceBucket":"10M+","amenities":["pool","gym"],"images":["https://placehold.co/600x400?text=land+1092"],"createdAt":"2023-11-01T04:43:22.371Z"},"1":{"id":1095,"title_en":"land in Chumphon #7","title_th":"ที่ดิน ในชุมพร #7","province":"Chumphon","province_th":"ชุมพร","type":"land","price":12687706,"priceBucket":"10M+","amenities":["security","parking","wifi","gym"],"images":["https://placehold.co/600x400?text=land+1096"],"createdAt":"2024-06-18T03:32:04.620Z"},"2":{"id":1099,"title_en":"land in Chumphon #11","title_th":"ที่ดิน ในชุมพร #11","province":"Chumphon","province_th":"ชุมพร","type":"land","price":15864367,"priceBucket":"10M+","amenities":["security","wifi","parking"],"images":["https://placehold.co/600x400?text=land+1100"],"createdAt":"2021-04-07T13:36:20.731Z"},"3":{"id":1103,"title_en":"land in Chumphon #15","title_th":"ที่ดิน ในชุมพร #15","province":"Chumphon","province_th":"ชุมพร","type":"land","price":13090686,"priceBucket":"10M+","amenities":["security","pool","wifi","gym","parking","garden"],"images":["https://placehold.co/600x400?text=land+1104"],"createdAt":"2025-07-23T17:06:26.215Z"}},"dirtCount":0,"index":[["15",{"0":{"3":1},"1":{"3":1}}],["11",{"0":{"2":1},"1":{"2":1}}],["7",{"0":{"1":1},"1":{"1":1}}],["located",{"2":{"0":1,"1":1,"2":1,"3":1}}],["lovely",{"2":{"0":1,"1":1,"2":1,"3":1}}],["land",{"0":{"0":1,"1":1,"2":1,"3":1},"2":{"0":1,"1":1,"2":1,"3":1}}],["ในชุมพร",{"1":{"0":1,"1":1,"2":1,"3":1}}],["ที่ดินตั้งอยู่ในชุมพร",{"3":{"0":1,"1":1,"2":1,"3":1}}],["ที่ดิน",{"1":{"0":1,"1":1,"2":1,"3":1}}],["3",{"0":{"0":1},"1":{"0":1}}],["chumphon",{"0":{"0":1,"1":1,"2":1,"3":1},"2":{"0":1,"1":1,"2":1,"3":1}}],["in",{"0":{"0":1,"1":1,"2":1,"3":1},"2":{"0":1,"1":1,"2":1,"3":1}}]],"serializationVersion":2}