{"documentCount":4,"nextId":4,"documentIds":{"0":579,"1":583,"2":587,"3":591},"fieldIds":{"title_en":0,"title_th":1,"description_en":2,"description_th":3},"fieldLength":{"0":[4,3,6,1],"1":[4,3,6,1],"2":[4,3,6,1],"3":[4,3,6,1]},"averageFieldLength":[4,3,6,1],"storedFields":{"0":{"id":579,"title_en":"land in Mukdahan #3","title_th":"ที่ดิน ในมุกดาหาร #3","province":"Mukdahan","province_th":"มุกดาหาร","type":"land","price":17350003,"priceBucket":"10M+","amenities":["gym","pool","wifi","security","parking"],"images":["https://placehold.co/600x400?text=land+580"],"createdAt":"2025-05-07T09:21:46.654Z"},"1":{"id":583,"title_en":"land in Mukdahan #7","title_th":"ที่ดิน ในมุกดาหาร #7","province":"Mukdahan","province_th":"มุกดาหาร","type":"land","price":10132545,"priceBucket":"10M+","amenities":["garden","security","parking","wifi"],"images":["https://placehold.co/600x400?text=land+584"],"createdAt":"2021-07-27T13:27:38.437Z"},"2":{"id":587,"title_en":"land in Mukdahan #11","title_th":"ที่ดิน ในมุกดาหาร #11","province":"Mukdahan","province_th":"มุกดาหาร","type":"land","price":18680762,"priceBucket":"10M+","amenities":["gym","pool","garden","parking","wifi","security"],"images":["https://placehold.co/600x400?text=land+588"],"createdAt":"2020-01-14T20:54:57.544Z"},"3":{"id":591,"title_en":"land in Mukdahan #15","title_th":"ที่ดิน ในมุกดาหาร #15","province":"Mukdahan","province_th":"มุกดาหาร","type":"land","price":7720723,"priceBucket":"5-10M","amenities":["garden","security","wifi","parking","gym","pool"],"images":["https://placehold.co/600x400?text=land+592"],"createdAt":"2021-08-26T09:35:03.623Z"}},"dirtCount":0,"index":[["15",{"0":{"3":1},"1":{"3":1}}],["11",{"0":{"2":1},"1":{"2":1}}],["7",{"0":{"1":1},"1":{"1":1}}],["located",{"2":{"0":1,"1":1,"2":1,"3":1}}],["lovely",{"2":{"0":1,"1":1,"2":1,"3":1}}],["land",{"0":{"0":1,"1":1,"2":1,"3":1},"2":{"0":1,"1":1,"2":1,"3":1}}],["ในมุกดาหาร",{"1":{"0":1,"1":1,"2":1,"3":1}}],["ที่ดินตั้งอยู่ในมุกดาหาร",{"3":{"0":1,"1":1,"2":1,"3":1}}],["ที่ดิน",{"1":{"0":1,"1":1,"2":1,"3":1}}],["3",{"0":{"0":1},"1":{"0":1}}],["mukdahan",{"0":{"0":1,"1":1,"2":1,"3":1},"2":{"0":1,"1":1,"2":1,"3":1}}],["in",{"0":{"0":1,"1":1,"2":1,"3":1},"2":{"0":1,"1":1,"2":1,"3":1}}]],"serializationVersion":2}